teamgenai/README.md
teamgenai/config.py
teamgenai/main.py
teamgenai/requirements.txt
teamgenai-2.0.0.dist-info/LICENSE
teamgenai-2.0.0.dist-info/METADATA
teamgenai-2.0.0.dist-info/WHEEL
teamgenai-2.0.0.dist-info/entry_points.txt
teamgenai-2.0.0.dist-info/top_level.txt
teamgenai-2.0.0.dist-info/RECORD
